README.rst
setup.cfg
setup.py
tgf/__init__.py
tgf/scripts/__init__.py
tgf/scripts/cli.py
type_goes_first.egg-info/PKG-INFO
type_goes_first.egg-info/SOURCES.txt
type_goes_first.egg-info/dependency_links.txt
type_goes_first.egg-info/entry_points.txt
type_goes_first.egg-info/not-zip-safe
type_goes_first.egg-info/requires.txt
type_goes_first.egg-info/top_level.txt