Metadata-Version: 1.0
Name: type-goes-first
Version: 0.0.2
Summary: Ensures that a FeatureCollection is declared early
Home-page: https://github.com/jacquestardie/tgf
Author: Jacques Tardie
Author-email: jacques@mapbox.com
License: MIT
Keywords: geojson,supermercado
Platform: UNKNOWN
